[
  
  { "emoji": "😀", "name": "활짝 웃는 얼굴", "category": "얼굴/표정" },
  { "emoji": "😁", "name": "눈웃음", "category": "얼굴/표정" },
  { "emoji": "😂", "name": "기쁨의 눈물", "category": "얼굴/표정" },
  { "emoji": "🤣", "name": "박장대소", "category": "얼굴/표정" },
  { "emoji": "😃", "name": "활짝 웃는 얼굴(작게)", "category": "얼굴/표정" },
  { "emoji": "😅", "name": "식은땀", "category": "얼굴/표정" },
  { "emoji": "😊", "name": "미소짓는 얼굴", "category": "얼굴/표정" },
  { "emoji": "😇", "name": "천사 얼굴", "category": "얼굴/표정" },
  { "emoji": "😉", "name": "윙크", "category": "얼굴/표정" },
  { "emoji": "😍", "name": "하트 눈", "category": "얼굴/표정" },
  { "emoji": "😘", "name": "키스", "category": "얼굴/표정" },
  { "emoji": "😗", "name": "키스(입다문)", "category": "얼굴/표정" },
  { "emoji": "😋", "name": "냠냠", "category": "얼굴/표정" },
  { "emoji": "😜", "name": "메롱", "category": "얼굴/표정" },
  { "emoji": "🤪", "name": "익살", "category": "얼굴/표정" },
  { "emoji": "😝", "name": "눈감고 메롱", "category": "얼굴/표정" },
  { "emoji": "🤑", "name": "돈눈", "category": "얼굴/표정" },
  { "emoji": "🤗", "name": "포옹", "category": "얼굴/표정" },
  { "emoji": "🤔", "name": "생각중", "category": "얼굴/표정" },
  { "emoji": "😐", "name": "무표정", "category": "얼굴/표정" },
  { "emoji": "😶", "name": "입 없는 얼굴", "category": "얼굴/표정" },
  { "emoji": "😏", "name": "능글맞은 표정", "category": "얼굴/표정" },
  { "emoji": "😒", "name": "심드렁", "category": "얼굴/표정" },
  { "emoji": "🙄", "name": "눈 굴리기", "category": "얼굴/표정" },
  { "emoji": "😬", "name": "찡그린 얼굴", "category": "얼굴/표정" },
  { "emoji": "🤥", "name": "거짓말", "category": "얼굴/표정" },
  { "emoji": "😌", "name": "만족", "category": "얼굴/표정" },
  { "emoji": "😔", "name": "슬픔", "category": "얼굴/표정" },
  { "emoji": "😪", "name": "졸림", "category": "얼굴/표정" },
  { "emoji": "🤤", "name": "침흘림", "category": "얼굴/표정" },
  { "emoji": "😴", "name": "자는 얼굴", "category": "얼굴/표정" },
  { "emoji": "😷", "name": "마스크", "category": "얼굴/표정" },
  { "emoji": "🤒", "name": "아픈 얼굴", "category": "얼굴/표정" },
  { "emoji": "🤕", "name": "붕대 얼굴", "category": "얼굴/표정" },
  { "emoji": "🤢", "name": "구역질", "category": "얼굴/표정" },
  { "emoji": "🤮", "name": "토함", "category": "얼굴/표정" },
  { "emoji": "🥵", "name": "더움", "category": "얼굴/표정" },
  { "emoji": "🥶", "name": "추움", "category": "얼굴/표정" },
  { "emoji": "🥴", "name": "어지러움", "category": "얼굴/표정" },
  { "emoji": "😵", "name": "혼란", "category": "얼굴/표정" },
  { "emoji": "🤯", "name": "터지는 머리", "category": "얼굴/표정" },
  { "emoji": "🤠", "name": "카우보이", "category": "얼굴/표정" },
  { "emoji": "🥳", "name": "파티 얼굴", "category": "얼굴/표정" },
  { "emoji": "😎", "name": "선글라스", "category": "얼굴/표정" },
  { "emoji": "🤓", "name": "너드", "category": "얼굴/표정" },
  { "emoji": "🧐", "name": "수색", "category": "얼굴/표정" },
  { "emoji": "😕", "name": "당황", "category": "얼굴/표정" },
  { "emoji": "🙃", "name": "뒤집힌 얼굴", "category": "얼굴/표정" },

  
  { "emoji": "🫠", "name": "녹는 얼굴", "category": "얼굴/표정" },
  { "emoji": "🥹", "name": "감동받아 눈물 글썽", "category": "얼굴/표정" },
  { "emoji": "🤫", "name": "쉬", "category": "얼굴/표정" },
  { "emoji": "🤬", "name": "심한 욕설", "category": "얼굴/표정" },
  { "emoji": "🥺", "name": "애원하는 얼굴", "category": "얼굴/표정" },
  { "emoji": "🥱", "name": "하품", "category": "얼굴/표정" },
  { "emoji": "😤", "name": "콧김", "category": "얼굴/표정" },
  { "emoji": "😮", "name": "입 벌린 얼굴", "category": "얼굴/표정" },
  { "emoji": "😯", "name": "조용한 얼굴", "category": "얼굴/표정" },
  { "emoji": "😥", "name": "실망했지만 안도", "category": "얼굴/표정" },
  { "emoji": "😭", "name": "엉엉 우는 얼굴", "category": "얼굴/표정" },
  { "emoji": "😱", "name": "비명", "category": "얼굴/표정" },
  { "emoji": "😖", "name": "괴로움", "category": "얼굴/표정" },
  { "emoji": "😠", "name": "화남", "category": "얼굴/표정" },
  { "emoji": "😡", "name": "매우 화남", "category": "얼굴/표정" },
  { "emoji": "🤡", "name": "광대", "category": "얼굴/표정" },
  { "emoji": "💩", "name": "똥", "category": "얼굴/표정" },
  { "emoji": "👿", "name": "화난 악마", "category": "얼굴/표정" },
  { "emoji": "😈", "name": "미소짓는 악마", "category": "얼굴/표정" },
  { "emoji": "👹", "name": "오니", "category": "얼굴/표정" },
  { "emoji": "👺", "name": "텐구", "category": "얼굴/표정" },
  { "emoji": "💀", "name": "해골", "category": "얼굴/표정" },
  { "emoji": "👻", "name": "유령", "category": "얼굴/표정" },
  { "emoji": "👽", "name": "외계인", "category": "얼굴/표정" },
  { "emoji": "🤖", "name": "로봇", "category": "얼굴/표정" },
  { "emoji": "🫶", "name": "손 하트", "category": "얼굴/표정" },
  { "emoji": "🫡", "name": "경례하는 얼굴", "category": "얼굴/표정" },
  { "emoji": "🫣", "name": "엿보는 얼굴", "category": "얼굴/표정" },
  { "emoji": "🫦", "name": "입술 깨물기", "category": "얼굴/표정" },
  { "emoji": "👀", "name": "두리번", "category": "얼굴/표정" },
  { "emoji": "🧠", "name": "뇌", "category": "얼굴/표정" },
  { "emoji": "🫥", "name": "점선 얼굴", "category": "얼굴/표정" },

  
  { "emoji": "🙋‍♂️", "name": "손드는 남자", "category": "사람/행동" },
  { "emoji": "🙋‍♀️", "name": "손드는 여자", "category": "사람/행동" },
  { "emoji": "🙆‍♀️", "name": "OK 제스처 여자", "category": "사람/행동" },
  { "emoji": "🙆‍♂️", "name": "OK 제스처 남자", "category": "사람/행동" },
  { "emoji": "🙇‍♂️", "name": "인사 남자", "category": "사람/행동" },
  { "emoji": "🙇‍♀️", "name": "인사 여자", "category": "사람/행동" },
  { "emoji": "🙅‍♂️", "name": "거절 남자", "category": "사람/행동" },
  { "emoji": "🙅‍♀️", "name": "거절 여자", "category": "사람/행동" },
  { "emoji": "🙎‍♂️", "name": "찡그림 남자", "category": "사람/행동" },
  { "emoji": "🙎‍♀️", "name": "찡그림 여자", "category": "사람/행동" },
  { "emoji": "👍", "name": "엄지 척", "category": "사람/행동" },
  { "emoji": "👎", "name": "엄지 아래", "category": "사람/행동" },
  { "emoji": "👏", "name": "박수", "category": "사람/행동" },
  { "emoji": "🙏", "name": "기도", "category": "사람/행동" },
  { "emoji": "🤝", "name": "악수", "category": "사람/행동" },
  { "emoji": "✌️", "name": "브이", "category": "사람/행동" },
  { "emoji": "🤟", "name": "아이러브유", "category": "사람/행동" },
  { "emoji": "🤲", "name": "두 손 모음", "category": "사람/행동" },
  { "emoji": "👐", "name": "손 벌림", "category": "사람/행동" },
  { "emoji": "🙌", "name": "두 손 번쩍", "category": "사람/행동" },
  { "emoji": "🤌", "name": "이탈리아 손짓", "category": "사람/행동" },

  
  { "emoji": "👨‍⚕️", "name": "남자 의사", "category": "사람/행동" },
  { "emoji": "👩‍⚕️", "name": "여자 의사", "category": "사람/행동" },
  { "emoji": "👨‍🎓", "name": "남학생", "category": "사람/행동" },
  { "emoji": "👩‍🎓", "name": "여학생", "category": "사람/행동" },
  { "emoji": "👨‍🏫", "name": "남자 선생님", "category": "사람/행동" },
  { "emoji": "👩‍🏫", "name": "여자 선생님", "category": "사람/행동" },
  { "emoji": "👨‍⚖️", "name": "남자 판사", "category": "사람/행동" },
  { "emoji": "👩‍⚖️", "name": "여자 판사", "category": "사람/행동" },
  { "emoji": "👨‍🌾", "name": "남자 농부", "category": "사람/행동" },
  { "emoji": "👩‍🌾", "name": "여자 농부", "category": "사람/행동" },
  { "emoji": "👨‍🍳", "name": "남자 요리사", "category": "사람/행동" },
  { "emoji": "👩‍🍳", "name": "여자 요리사", "category": "사람/행동" },
  { "emoji": "👨‍🔧", "name": "남자 정비공", "category": "사람/행동" },
  { "emoji": "👩‍🔧", "name": "여자 정비공", "category": "사람/행동" },
  { "emoji": "👨‍🏭", "name": "남자 공장 노동자", "category": "사람/행동" },
  { "emoji": "👩‍🏭", "name": "여자 공장 노동자", "category": "사람/행동" },
  { "emoji": "👨‍💼", "name": "남자 회사원", "category": "사람/행동" },
  { "emoji": "👩‍💼", "name": "여자 회사원", "category": "사람/행동" },
  { "emoji": "👨‍🔬", "name": "남자 과학자", "category": "사람/행동" },
  { "emoji": "👩‍🔬", "name": "여자 과학자", "category": "사람/행동" },
  { "emoji": "👨‍💻", "name": "남자 개발자", "category": "사람/행동" },
  { "emoji": "👩‍💻", "name": "여자 개발자", "category": "사람/행동" },
  { "emoji": "👨‍🎤", "name": "남자 가수", "category": "사람/행동" },
  { "emoji": "👩‍🎤", "name": "여자 가수", "category": "사람/행동" },
  { "emoji": "👨‍🎨", "name": "남자 예술가", "category": "사람/행동" },
  { "emoji": "👩‍🎨", "name": "여자 예술가", "category": "사람/행동" },
  { "emoji": "👨‍✈️", "name": "남자 조종사", "category": "사람/행동" },
  { "emoji": "👩‍✈️", "name": "여자 조종사", "category": "사람/행동" },
  { "emoji": "👨‍🚀", "name": "남자 우주비행사", "category": "사람/행동" },
  { "emoji": "👩‍🚀", "name": "여자 우주비행사", "category": "사람/행동" },
  { "emoji": "👨‍🚒", "name": "남자 소방관", "category": "사람/행동" },
  { "emoji": "👩‍🚒", "name": "여자 소방관", "category": "사람/행동" },
  { "emoji": "👮‍♂️", "name": "남자 경찰관", "category": "사람/행동" },
  { "emoji": "👮‍♀️", "name": "여자 경찰관", "category": "사람/행동" },
  { "emoji": "🕵️‍♂️", "name": "남자 탐정", "category": "사람/행동" },
  { "emoji": "🕵️‍♀️", "name": "여자 탐정", "category": "사람/행동" },
  { "emoji": "💂‍♂️", "name": "남자 경비원", "category": "사람/행동" },
  { "emoji": "💂‍♀️", "name": "여자 경비원", "category": "사람/행동" },
  { "emoji": "👷‍♂️", "name": "남자 건설 노동자", "category": "사람/행동" },
  { "emoji": "👷‍♀️", "name": "여자 건설 노동자", "category": "사람/행동" },
  { "emoji": "🤴", "name": "왕자", "category": "사람/행동" },
  { "emoji": "👸", "name": "공주", "category": "사람/행동" },
  { "emoji": "👳‍♂️", "name": "터번 쓴 남자", "category": "사람/행동" },
  { "emoji": "👳‍♀️", "name": "터번 쓴 여자", "category": "사람/행동" },
  { "emoji": "🧕", "name": "히잡 쓴 여자", "category": "사람/행동" },
  { "emoji": "🤵‍♂️", "name": "턱시도 입은 남자", "category": "사람/행동" },
  { "emoji": "🤵‍♀️", "name": "턱시도 입은 여자", "category": "사람/행동" },
  { "emoji": "👰‍♂️", "name": "면사포 쓴 남자", "category": "사람/행동" },
  { "emoji": "👰‍♀️", "name": "면사포 쓴 여자", "category": "사람/행동" },
  { "emoji": "🤰", "name": "임산부", "category": "사람/행동" },
  { "emoji": "🤱", "name": "모유 수유", "category": "사람/행동" },
  { "emoji": "🧑‍🍼", "name": "아기에게 젖병 물리는 사람", "category": "사람/행동" },
  { "emoji": "🧑‍🦰", "name": "빨간 머리", "category": "사람/행동" },
  { "emoji": "🧑‍🦱", "name": "곱슬 머리", "category": "사람/행동" },
  { "emoji": "🧑‍🦳", "name": "흰 머리", "category": "사람/행동" },
  { "emoji": "🧑‍🦲", "name": "대머리", "category": "사람/행동" },
  { "emoji": "🤷", "name": "어깨 으쓱", "category": "사람/행동" },
  { "emoji": "🤦", "name": "얼굴 가리기", "category": "사람/행동" },
  { "emoji": "🤞", "name": "행운을 빌어", "category": "사람/행동" },
  { "emoji": "🤙", "name": "전화해", "category": "사람/행동" },
  { "emoji": "💪", "name": "알통", "category": "사람/행동" },
  { "emoji": "🦵", "name": "다리", "category": "사람/행동" },
  { "emoji": "🦶", "name": "발", "category": "사람/행동" },
  { "emoji": "🤳", "name": "셀카", "category": "사람/행동" },
  { "emoji": "🧛", "name": "뱀파이어", "category": "사람/행동" },
  { "emoji": "🧜", "name": "인어", "category": "사람/행동" },
  { "emoji": "🧝", "name": "엘프", "category": "사람/행동" },
  { "emoji": "🧞", "name": "지니", "category": "사람/행동" },
  { "emoji": "🧟", "name": "좀비", "category": "사람/행동" },

  
  { "emoji": "🐶", "name": "강아지", "category": "동물/자연" },
  { "emoji": "🐱", "name": "고양이", "category": "동물/자연" },
  { "emoji": "🐭", "name": "쥐", "category": "동물/자연" },
  { "emoji": "🐹", "name": "햄스터", "category": "동물/자연" },
  { "emoji": "🐰", "name": "토끼", "category": "동물/자연" },
  { "emoji": "🦊", "name": "여우", "category": "동물/자연" },
  { "emoji": "🐻", "name": "곰", "category": "동물/자연" },
  { "emoji": "🐼", "name": "판다", "category": "동물/자연" },
  { "emoji": "🐨", "name": "코알라", "category": "동물/자연" },
  { "emoji": "🐯", "name": "호랑이", "category": "동물/자연" },
  { "emoji": "🦁", "name": "사자", "category": "동물/자연" },
  { "emoji": "🐮", "name": "소", "category": "동물/자연" },
  { "emoji": "🐷", "name": "돼지", "category": "동물/자연" },
  { "emoji": "🐸", "name": "개구리", "category": "동물/자연" },
  { "emoji": "🐵", "name": "원숭이", "category": "동물/자연" },
  { "emoji": "🐔", "name": "닭", "category": "동물/자연" },
  { "emoji": "🦄", "name": "유니콘", "category": "동물/자연" },
  { "emoji": "🐝", "name": "벌", "category": "동물/자연" },
  { "emoji": "🐢", "name": "거북이", "category": "동물/자연" },
  { "emoji": "🐬", "name": "돌고래", "category": "동물/자연" },
  { "emoji": "🌳", "name": "나무", "category": "동물/자연" },

  
  { "emoji": "🦅", "name": "독수리", "category": "동물/자연" },
  { "emoji": "🦆", "name": "오리", "category": "동물/자연" },
  { "emoji": "🦉", "name": "부엉이", "category": "동물/자연" },
  { "emoji": "🦇", "name": "박쥐", "category": "동물/자연" },
  { "emoji": "🐺", "name": "늑대", "category": "동물/자연" },
  { "emoji": "🐗", "name": "멧돼지", "category": "동물/자연" },
  { "emoji": "🐴", "name": "말", "category": "동물/자연" },
  { "emoji": "🦓", "name": "얼룩말", "category": "동물/자연" },
  { "emoji": "🦒", "name": "기린", "category": "동물/자연" },
  { "emoji": "🐘", "name": "코끼리", "category": "동물/자연" },
  { "emoji": "🦏", "name": "코뿔소", "category": "동물/자연" },
  { "emoji": "🐫", "name": "낙타", "category": "동물/자연" },
  { "emoji": "🦍", "name": "고릴라", "category": "동물/자연" },
  { "emoji": "🦧", "name": "오랑우탄", "category": "동물/자연" },
  { "emoji": "🐕", "name": "개", "category": "동물/자연" },
  { "emoji": "🐩", "name": "푸들", "category": "동물/자연" },
  { "emoji": "🐈", "name": "검은 고양이", "category": "동물/자연" },
  { "emoji": "🐅", "name": "표범", "category": "동물/자연" },
  { "emoji": "🐆", "name": "치타", "category": "동물/자연" },
  { "emoji": "🐖", "name": "새끼 돼지", "category": "동물/자연" },
  { "emoji": "🐐", "name": "염소", "category": "동물/자연" },
  { "emoji": "🐑", "name": "양", "category": "동물/자연" },
  { "emoji": "🐒", "name": "원숭이(작게)", "category": "동물/자연" },
  { "emoji": "🦥", "name": "나무늘보", "category": "동물/자연" },
  { "emoji": "🦦", "name": "수달", "category": "동물/자연" },
  { "emoji": "🦨", "name": "스컹크", "category": "동물/자연" },
  { "emoji": "🦘", "name": "캥거루", "category": "동물/자연" },
  { "emoji": "🦡", "name": "오소리", "category": "동물/자연" },
  { "emoji": "🦃", "name": "칠면조", "category": "동물/자연" },
  { "emoji": "🕊️", "name": "비둘기", "category": "동물/자연" },
  { "emoji": "🦢", "name": "백조", "category": "동물/자연" },
  { "emoji": "🦜", "name": "앵무새", "category": "동물/자연" },
  { "emoji": "🦚", "name": "공작", "category": "동물/자연" },
  { "emoji": "🐧", "name": "펭귄", "category": "동물/자연" },
  { "emoji": "🐊", "name": "악어", "category": "동물/자연" },
  { "emoji": "🐍", "name": "뱀", "category": "동물/자연" },
  { "emoji": "🐲", "name": "용", "category": "동물/자연" },
  { "emoji": "🐳", "name": "고래", "category": "동물/자연" },
  { "emoji": "🐋", "name": "혹등고래", "category": "동물/자연" },
  { "emoji": "🦈", "name": "상어", "category": "동물/자연" },
  { "emoji": "🐙", "name": "문어", "category": "동물/자연" },
  { "emoji": "🐚", "name": "소라", "category": "동물/자연" },
  { "emoji": "🦀", "name": "게", "category": "동물/자연" },
  { "emoji": "🦐", "name": "새우", "category": "동물/자연" },
  { "emoji": "🦑", "name": "오징어", "category": "동물/자연" },
  { "emoji": "🐌", "name": "달팽이", "category": "동물/자연" },
  { "emoji": "🦋", "name": "나비", "category": "동물/자연" },
  { "emoji": "🐛", "name": "애벌레", "category": "동물/자연" },
  { "emoji": "🐜", "name": "개미", "category": "동물/자연" },
  { "emoji": "🐞", "name": "무당벌레", "category": "동물/자연" },
  { "emoji": "🦗", "name": "귀뚜라미", "category": "동물/자연" },
  { "emoji": "🕷️", "name": "거미", "category": "동물/자연" },
  { "emoji": "🦂", "name": "전갈", "category": "동물/자연" },
  { "emoji": "💐", "name": "꽃다발", "category": "동물/자연" },
  { "emoji": "🌸", "name": "벚꽃", "category": "동물/자연" },
  { "emoji": "💮", "name": "참 잘했어요", "category": "동물/자연" },
  { "emoji": "🏵️", "name": "로제트", "category": "동물/자연" },
  { "emoji": "🌹", "name": "장미", "category": "동물/자연" },
  { "emoji": "🥀", "name": "시든 장미", "category": "동물/자연" },
  { "emoji": "🌺", "name": "히비스커스", "category": "동물/자연" },
  { "emoji": "🌻", "name": "해바라기", "category": "동물/자연" },
  { "emoji": "🌼", "name": "데이지", "category": "동물/자연" },
  { "emoji": "🌷", "name": "튤립", "category": "동물/자연" },
  { "emoji": "🌱", "name": "새싹", "category": "동물/자연" },
  { "emoji": "🌲", "name": "소나무", "category": "동물/자연" },
  { "emoji": "🌴", "name": "야자수", "category": "동물/자연" },
  { "emoji": "🌵", "name": "선인장", "category": "동물/자연" },
  { "emoji": "🌾", "name": "벼", "category": "동물/자연" },
  { "emoji": "🌿", "name": "허브", "category": "동물/자연" },
  { "emoji": "☘️", "name": "세잎클로버", "category": "동물/자연" },
  { "emoji": "🍀", "name": "네잎클로버", "category": "동물/자연" },
  { "emoji": "🍁", "name": "단풍", "category": "동물/자연" },
  { "emoji": "🍂", "name": "낙엽", "category": "동물/자연" },
  { "emoji": "🍃", "name": "흩날리는 잎", "category": "동물/자연" },

  
  { "emoji": "🍔", "name": "햄버거", "category": "음식/음료" },
  { "emoji": "🍟", "name": "감자튀김", "category": "음식/음료" },
  { "emoji": "🍕", "name": "피자", "category": "음식/음료" },
  { "emoji": "🌭", "name": "핫도그", "category": "음식/음료" },
  { "emoji": "🍿", "name": "팝콘", "category": "음식/음료" },
  { "emoji": "🍜", "name": "라면", "category": "음식/음료" },
  { "emoji": "🍣", "name": "초밥", "category": "음식/음료" },
  { "emoji": "🍩", "name": "도넛", "category": "음식/음료" },
  { "emoji": "🍪", "name": "쿠키", "category": "음식/음료" },
  { "emoji": "🎂", "name": "케이크", "category": "음식/음료" },
  { "emoji": "🍰", "name": "조각케이크", "category": "음식/음료" },
  { "emoji": "🍫", "name": "초콜릿", "category": "음식/음료" },
  { "emoji": "🍬", "name": "사탕", "category": "음식/음료" },
  { "emoji": "🍎", "name": "사과", "category": "음식/음료" },
  { "emoji": "🍇", "name": "포도", "category": "음식/음료" },
  { "emoji": "🍓", "name": "딸기", "category": "음식/음료" },
  { "emoji": "🍉", "name": "수박", "category": "음식/음료" },
  { "emoji": "🍌", "name": "바나나", "category": "음식/음료" },
  { "emoji": "☕", "name": "커피", "category": "음식/음료" },
  { "emoji": "🥤", "name": "음료수", "category": "음식/음료" },

  
  { "emoji": "🥝", "name": "키위", "category": "음식/음료" },
  { "emoji": "🥥", "name": "코코넛", "category": "음식/음료" },
  { "emoji": "🥑", "name": "아보카도", "category": "음식/음료" },
  { "emoji": "🍆", "name": "가지", "category": "음식/음료" },
  { "emoji": "🥔", "name": "감자", "category": "음식/음료" },
  { "emoji": "🥕", "name": "당근", "category": "음식/음료" },
  { "emoji": "🌽", "name": "옥수수", "category": "음식/음료" },
  { "emoji": "🌶️", "name": "고추", "category": "음식/음료" },
  { "emoji": "🥒", "name": "오이", "category": "음식/음료" },
  { "emoji": "🥬", "name": "상추", "category": "음식/음료" },
  { "emoji": "🥦", "name": "브로콜리", "category": "음식/음료" },
  { "emoji": "🧄", "name": "마늘", "category": "음식/음료" },
  { "emoji": "🧅", "name": "양파", "category": "음식/음료" },
  { "emoji": "🍄", "name": "버섯", "category": "음식/음료" },
  { "emoji": "🥜", "name": "땅콩", "category": "음식/음료" },
  { "emoji": "🌰", "name": "밤", "category": "음식/음료" },
  { "emoji": "🍞", "name": "빵", "category": "음식/음료" },
  { "emoji": "🥐", "name": "크루아상", "category": "음식/음료" },
  { "emoji": "🥖", "name": "바게트", "category": "음식/음료" },
  { "emoji": "🥨", "name": "프레즐", "category": "음식/음료" },
  { "emoji": "🥯", "name": "베이글", "category": "음식/음료" },
  { "emoji": "🥞", "name": "팬케이크", "category": "음식/음료" },
  { "emoji": "🧇", "name": "와플", "category": "음식/음료" },
  { "emoji": "🧀", "name": "치즈", "category": "음식/음료" },
  { "emoji": "🍖", "name": "고기", "category": "음식/음료" },
  { "emoji": "🍗", "name": "닭다리", "category": "음식/음료" },
  { "emoji": "🥩", "name": "스테이크", "category": "음식/음료" },
  { "emoji": "🥓", "name": "베이컨", "category": "음식/음료" },
  { "emoji": "🥚", "name": "달걀", "category": "음식/음료" },
  { "emoji": "🍳", "name": "계란프라이", "category": "음식/음료" },
  { "emoji": "🥘", "name": "파에야", "category": "음식/음료" },
  { "emoji": "🍲", "name": "찌개", "category": "음식/음료" },
  { "emoji": "🥣", "name": "시리얼", "category": "음식/음료" },
  { "emoji": "🥗", "name": "샐러드", "category": "음식/음료" },
  { "emoji": "🧂", "name": "소금", "category": "음식/음료" },
  { "emoji": "🥫", "name": "통조림", "category": "음식/음료" },
  { "emoji": "🍱", "name": "도시락", "category": "음식/음료" },
  { "emoji": "🍘", "name": "센베이", "category": "음식/음료" },
  { "emoji": "🍙", "name": "주먹밥", "category": "음식/음료" },
  { "emoji": "🍚", "name": "밥", "category": "음식/음료" },
  { "emoji": "🍛", "name": "카레", "category": "음식/음료" },
  { "emoji": "🍝", "name": "스파게티", "category": "음식/음료" },
  { "emoji": "🍠", "name": "고구마", "category": "음식/음료" },
  { "emoji": "🍢", "name": "어묵", "category": "음식/음료" },
  { "emoji": "🍧", "name": "빙수", "category": "음식/음료" },
  { "emoji": "🍨", "name": "아이스크림", "category": "음식/음료" },
  { "emoji": "🍮", "name": "푸딩", "category": "음식/음료" },
  { "emoji": "🍯", "name": "꿀", "category": "음식/음료" },
  { "emoji": "🥛", "name": "우유", "category": "음식/음료" },
  { "emoji": "🍵", "name": "녹차", "category": "음식/음료" },
  { "emoji": "🍶", "name": "사케", "category": "음식/음료" },
  { "emoji": "🍾", "name": "샴페인", "category": "음식/음료" },
  { "emoji": "🍷", "name": "와인", "category": "음식/음료" },
  { "emoji": "🍸", "name": "칵테일", "category": "음식/음료" },
  { "emoji": "🍹", "name": "트로피컬 드링크", "category": "음식/음료" },
  { "emoji": "🍺", "name": "맥주", "category": "음식/음료" },
  { "emoji": "🍻", "name": "건배", "category": "음식/음료" },
  { "emoji": "🥂", "name": "샴페인 건배", "category": "음식/음료" },
  { "emoji": "🥃", "name": "위스키", "category": "음식/음료" },
  { "emoji": "🥣", "name": "그릇", "category": "음식/음료" },
  { "emoji": "🥢", "name": "젓가락", "category": "음식/음료" },
  { "emoji": "🍽️", "name": "식기", "category": "음식/음료" },
  { "emoji": "🍴", "name": "포크와 나이프", "category": "음식/음료" },
  { "emoji": "🥄", "name": "숟가락", "category": "음식/음료" },
  { "emoji": "🫙", "name": "병", "category": "음식/음료" },

  
  { "emoji": "⚽", "name": "축구공", "category": "스포츠/활동" },
  { "emoji": "🏀", "name": "농구공", "category": "스포츠/활동" },
  { "emoji": "🏈", "name": "미식축구공", "category": "스포츠/활동" },
  { "emoji": "⚾", "name": "야구공", "category": "스포츠/활동" },
  { "emoji": "🏐", "name": "배구공", "category": "스포츠/활동" },
  { "emoji": "🎾", "name": "테니스", "category": "스포츠/활동" },
  { "emoji": "🏓", "name": "탁구", "category": "스포츠/활동" },
  { "emoji": "🏸", "name": "배드민턴", "category": "스포츠/활동" },
  { "emoji": "🎳", "name": "볼링", "category": "스포츠/활동" },
  { "emoji": "🥊", "name": "복싱글러브", "category": "스포츠/활동" },
  { "emoji": "🧘‍♀️", "name": "요가", "category": "스포츠/활동" },
  { "emoji": "🏄‍♂️", "name": "서핑", "category": "스포츠/활동" },
  { "emoji": "🚴‍♀️", "name": "자전거타기", "category": "스포츠/활동" },
  { "emoji": "🎮", "name": "게임패드", "category": "스포츠/활동" },
  { "emoji": "🎲", "name": "주사위", "category": "스포츠/활동" },
  { "emoji": "🎯", "name": "다트", "category": "스포츠/활동" },
  { "emoji": "🏆", "name": "트로피", "category": "스포츠/활동" },

  
  { "emoji": "🥋", "name": "도복", "category": "스포츠/활동" },
  { "emoji": "🎽", "name": "러닝셔츠", "category": "스포츠/활동" },
  { "emoji": "🏅", "name": "메달", "category": "스포츠/활동" },
  { "emoji": "🥇", "name": "금메달", "category": "스포츠/활동" },
  { "emoji": "🥈", "name": "은메달", "category": "스포츠/활동" },
  { "emoji": "🥉", "name": "동메달", "category": "스포츠/활동" },
  { "emoji": "🎗️", "name": "리본", "category": "스포츠/활동" },
  { "emoji": "🎫", "name": "티켓", "category": "스포츠/활동" },
  { "emoji": "🎪", "name": "서커스", "category": "스포츠/활동" },
  { "emoji": "🎭", "name": "가면", "category": "스포츠/활동" },
  { "emoji": "🎨", "name": "팔레트", "category": "스포츠/활동" },
  { "emoji": "🎬", "name": "슬레이트", "category": "스포츠/활동" },
  { "emoji": "🎤", "name": "마이크", "category": "스포츠/활동" },
  { "emoji": "🎧", "name": "헤드폰", "category": "스포츠/활동" },
  { "emoji": "🎼", "name": "악보", "category": "스포츠/활동" },
  { "emoji": "🎹", "name": "키보드", "category": "스포츠/활동" },
  { "emoji": "🥁", "name": "드럼", "category": "스포츠/활동" },
  { "emoji": "🎷", "name": "색소폰", "category": "스포츠/활동" },
  { "emoji": "🎺", "name": "트럼펫", "category": "스포츠/활동" },
  { "emoji": "🎸", "name": "기타", "category": "스포츠/활동" },
  { "emoji": "🎻", "name": "바이올린", "category": "스포츠/활동" },
  { "emoji": "🧩", "name": "퍼즐", "category": "스포츠/활동" },
  { "emoji": "♟️", "name": "체스", "category": "스포츠/활동" },
  { "emoji": "🪀", "name": "요요", "category": "스포츠/활동" },
  { "emoji": "🪁", "name": "연", "category": "스포츠/활동" },
  { "emoji": "🎱", "name": "당구", "category": "스포츠/활동" },
  { "emoji": "🥏", "name": "프리스비", "category": "스포츠/활동" },

  
  { "emoji": "🚗", "name": "자동차", "category": "탈것/교통" },
  { "emoji": "🚕", "name": "택시", "category": "탈것/교통" },
  { "emoji": "🚌", "name": "버스", "category": "탈것/교통" },
  { "emoji": "🚓", "name": "경찰차", "category": "탈것/교통" },
  { "emoji": "🚑", "name": "구급차", "category": "탈것/교통" },
  { "emoji": "🚒", "name": "소방차", "category": "탈것/교통" },
  { "emoji": "🚚", "name": "트럭", "category": "탈것/교통" },
  { "emoji": "🚙", "name": "SUV", "category": "탈것/교통" },
  { "emoji": "🚲", "name": "자전거", "category": "탈것/교통" },
  { "emoji": "🏍️", "name": "오토바이", "category": "탈것/교통" },
  { "emoji": "✈️", "name": "비행기", "category": "탈것/교통" },
  { "emoji": "🚁", "name": "헬리콥터", "category": "탈것/교통" },
  { "emoji": "🚤", "name": "보트", "category": "탈것/교통" },
  { "emoji": "🚢", "name": "배", "category": "탈것/교통" },
  { "emoji": "🚀", "name": "로켓", "category": "탈것/교통" },
  { "emoji": "🛴", "name": "킥보드", "category": "탈것/교통" },

  
  { "emoji": "🚄", "name": "고속철도", "category": "탈것/교통" },
  { "emoji": "🚅", "name": "신칸센", "category": "탈것/교통" },
  { "emoji": "🚈", "name": "경전철", "category": "탈것/교통" },
  { "emoji": "🚂", "name": "증기기관차", "category": "탈것/교통" },
  { "emoji": "🚃", "name": "전차", "category": "탈것/교통" },
  { "emoji": "🚋", "name": "트램", "category": "탈것/교통" },
  { "emoji": "🚠", "name": "케이블카", "category": "탈것/교통" },
  { "emoji": "🚟", "name": "현수식 모노레일", "category": "탈것/교통" },
  { "emoji": "✈️", "name": "비행기", "category": "탈것/교통" },
  { "emoji": "🛩️", "name": "소형 비행기", "category": "탈것/교통" },
  { "emoji": "🛫", "name": "이륙", "category": "탈것/교통" },
  { "emoji": "🛬", "name": "착륙", "category": "탈것/교통" },
  { "emoji": "🛰️", "name": "인공위성", "category": "탈것/교통" },
  { "emoji": "🛸", "name": "UFO", "category": "탈것/교통" },
  { "emoji": "🛶", "name": "카누", "category": "탈것/교통" },
  { "emoji": "⛵", "name": "요트", "category": "탈것/교통" },
  { "emoji": "⚓", "name": "닻", "category": "탈것/교통" },
  { "emoji": "⛽", "name": "주유소", "category": "탈것/교통" },
  { "emoji": "🚦", "name": "신호등", "category": "탈것/교통" },
  { "emoji": "🚧", "name": "공사중", "category": "탈것/교통" },

  
  { "emoji": "🏠", "name": "집", "category": "장소/건물" },
  { "emoji": "🏡", "name": "단독주택", "category": "장소/건물" },
  { "emoji": "🏢", "name": "사무실", "category": "장소/건물" },
  { "emoji": "🏥", "name": "병원", "category": "장소/건물" },
  { "emoji": "🏫", "name": "학교", "category": "장소/건물" },
  { "emoji": "🏦", "name": "은행", "category": "장소/건물" },
  { "emoji": "🏨", "name": "호텔", "category": "장소/건물" },
  { "emoji": "🏛️", "name": "관공서", "category": "장소/건물" },
  { "emoji": "🏰", "name": "성", "category": "장소/건물" },
  { "emoji": "🏯", "name": "일본성", "category": "장소/건물" },

  
  { "emoji": "🏗️", "name": "건설 현장", "category": "장소/건물" },
  { "emoji": "🏘️", "name": "주택 단지", "category": "장소/건물" },
  { "emoji": "🏚️", "name": "폐가", "category": "장소/건물" },
  { "emoji": "🏛️", "name": "고대 건축물", "category": "장소/건물" },
  { "emoji": "🏟️", "name": "경기장", "category": "장소/건물" },
  { "emoji": "🏞️", "name": "국립공원", "category": "장소/건물" },
  { "emoji": "🏜️", "name": "사막", "category": "장소/건물" },
  { "emoji": "🏝️", "name": "무인도", "category": "장소/건물" },
  { "emoji": "⛰️", "name": "산", "category": "장소/건물" },
  { "emoji": "🌋", "name": "화산", "category": "장소/건물" },
  { "emoji": "⛲", "name": "분수", "category": "장소/건물" },
  { "emoji": "⛺", "name": "텐트", "category": "장소/건물" },
  { "emoji": "🏭", "name": "공장", "category": "장소/건물" },
  { "emoji": "🏬", "name": "백화점", "category": "장소/건물" },
  { "emoji": "🏪", "name": "편의점", "category": "장소/건물" },
  { "emoji": "🏩", "name": "러브호텔", "category": "장소/건물" },
  { "emoji": "🏤", "name": "우체국", "category": "장소/건물" },
  { "emoji": "💒", "name": "교회", "category": "장소/건물" },
  { "emoji": "🕌", "name": "모스크", "category": "장소/건물" },
  { "emoji": "🕍", "name": "유대교 회당", "category": "장소/건물" },
  { "emoji": "⛩️", "name": "신사", "category": "장소/건물" },
  { "emoji": "🕋", "name": "카바", "category": "장소/건물" },
  { "emoji": "🌉", "name": "밤의 다리", "category": "장소/건물" },
  { "emoji": "🌃", "name": "야경", "category": "장소/건물" },
  { "emoji": "🏙️", "name": "도시 풍경", "category": "장소/건물" },
  { "emoji": "🌇", "name": "일출", "category": "장소/건물" },
  { "emoji": "🌅", "name": "일몰", "category": "장소/건물" },
  { "emoji": "🎡", "name": "관람차", "category": "장소/건물" },
  { "emoji": "🎢", "name": "롤러코스터", "category": "장소/건물" },
  { "emoji": "🎠", "name": "회전목마", "category": "장소/건물" },
  { "emoji": "🗽", "name": "자유의 여신상", "category": "장소/건물" },
  { "emoji": "🗿", "name": "모아이", "category": "장소/건물" },

  
  { "emoji": "⏰", "name": "알람 시계", "category": "시간/날씨" },
  { "emoji": "🕰️", "name": "탁상시계", "category": "시간/날씨" },
  { "emoji": "📅", "name": "달력", "category": "시간/날씨" },
  { "emoji": "📆", "name": "찢는달력", "category": "시간/날씨" },
  { "emoji": "🌞", "name": "해", "category": "시간/날씨" },
  { "emoji": "🌝", "name": "보름달", "category": "시간/날씨" },
  { "emoji": "🌜", "name": "초승달", "category": "시간/날씨" },
  { "emoji": "🌧️", "name": "비", "category": "시간/날씨" },
  { "emoji": "⛈️", "name": "천둥번개", "category": "시간/날씨" },
  { "emoji": "❄️", "name": "눈송이", "category": "시간/날씨" },
  { "emoji": "🌈", "name": "무지개", "category": "시간/날씨" },

  
  { "emoji": "⏱️", "name": "스톱워치", "category": "시간/날씨" },
  { "emoji": "⏲️", "name": "타이머", "category": "시간/날씨" },
  { "emoji": "🕛", "name": "12시", "category": "시간/날씨" },
  { "emoji": "🕧", "name": "12시 30분", "category": "시간/날씨" },
  { "emoji": "🕐", "name": "1시", "category": "시간/날씨" },
  { "emoji": "🕜", "name": "1시 30분", "category": "시간/날씨" },
  { "emoji": "🕑", "name": "2시", "category": "시간/날씨" },
  { "emoji": "🕝", "name": "2시 30분", "category": "시간/날씨" },
  { "emoji": "🕒", "name": "3시", "category": "시간/날씨" },
  { "emoji": "🕞", "name": "3시 30분", "category": "시간/날씨" },
  { "emoji": "🕓", "name": "4시", "category": "시간/날씨" },
  { "emoji": "🕟", "name": "4시 30분", "category": "시간/날씨" },
  { "emoji": "🕔", "name": "5시", "category": "시간/날씨" },
  { "emoji": "🕠", "name": "5시 30분", "category": "시간/날씨" },
  { "emoji": "🕕", "name": "6시", "category": "시간/날씨" },
  { "emoji": "🕡", "name": "6시 30분", "category": "시간/날씨" },
  { "emoji": "🕖", "name": "7시", "category": "시간/날씨" },
  { "emoji": "🕢", "name": "7시 30분", "category": "시간/날씨" },
  { "emoji": "🕗", "name": "8시", "category": "시간/날씨" },
  { "emoji": "🕣", "name": "8시 30분", "category": "시간/날씨" },
  { "emoji": "🕘", "name": "9시", "category": "시간/날씨" },
  { "emoji": "🕤", "name": "9시 30분", "category": "시간/날씨" },
  { "emoji": "🕙", "name": "10시", "category": "시간/날씨" },
  { "emoji": "🕥", "name": "10시 30분", "category": "시간/날씨" },
  { "emoji": "🕚", "name": "11시", "category": "시간/날씨" },
  { "emoji": "🕦", "name": "11시 30분", "category": "시간/날씨" },
  { "emoji": "🌑", "name": "삭", "category": "시간/날씨" },
  { "emoji": "🌒", "name": "초승달(오른쪽)", "category": "시간/날씨" },
  { "emoji": "🌓", "name": "상현달", "category": "시간/날씨" },
  { "emoji": "🌔", "name": "차가는 달", "category": "시간/날씨" },
  { "emoji": "🌕", "name": "보름달(얼굴없음)", "category": "시간/날씨" },
  { "emoji": "🌖", "name": "기우는 달", "category": "시간/날씨" },
  { "emoji": "🌗", "name": "하현달", "category": "시간/날씨" },
  { "emoji": "🌘", "name": "그믐달", "category": "시간/날씨" },
  { "emoji": "🌡️", "name": "온도계", "category": "시간/날씨" },
  { "emoji": "☀️", "name": "햇빛", "category": "시간/날씨" },
  { "emoji": "🌤️", "name": "해와 구름", "category": "시간/날씨" },
  { "emoji": "⛅", "name": "구름", "category": "시간/날씨" },
  { "emoji": "🌥️", "name": "해와 큰구름", "category": "시간/날씨" },
  { "emoji": "🌦️", "name": "해와 비", "category": "시간/날씨" },
  { "emoji": "☁️", "name": "뭉게구름", "category": "시간/날씨" },
  { "emoji": "🌨️", "name": "눈과 구름", "category": "시간/날씨" },
  { "emoji": "🌩️", "name": "번개와 구름", "category": "시간/날씨" },
  { "emoji": "🌪️", "name": "토네이도", "category": "시간/날씨" },
  { "emoji": "🌫️", "name": "안개", "category": "시간/날씨" },
  { "emoji": "🌬️", "name": "바람", "category": "시간/날씨" },
  { "emoji": "💧", "name": "물방울", "category": "시간/날씨" },
  { "emoji": "💦", "name": "땀방울", "category": "시간/날씨" },
  { "emoji": "🌊", "name": "파도", "category": "시간/날씨" },

  
  { "emoji": "📱", "name": "스마트폰", "category": "사물/도구" },
  { "emoji": "💻", "name": "노트북", "category": "사물/도구" },
  { "emoji": "🖥️", "name": "데스크탑", "category": "사물/도구" },
  { "emoji": "🖨️", "name": "프린터", "category": "사물/도구" },
  { "emoji": "📷", "name": "카메라", "category": "사물/도구" },
  { "emoji": "💡", "name": "전구", "category": "사물/도구" },
  { "emoji": "🔒", "name": "자물쇠", "category": "사물/도구" },
  { "emoji": "🔑", "name": "열쇠", "category": "사물/도구" },
  { "emoji": "🧯", "name": "소화기", "category": "사물/도구" },
  { "emoji": "📦", "name": "박스", "category": "사물/도구" },

  
  { "emoji": "☎️", "name": "전화기", "category": "사물/도구" },
  { "emoji": "📞", "name": "수화기", "category": "사물/도구" },
  { "emoji": "📠", "name": "팩스", "category": "사물/도구" },
  { "emoji": "🔋", "name": "배터리", "category": "사물/도구" },
  { "emoji": "🔌", "name": "플러그", "category": "사물/도구" },
  { "emoji": "💽", "name": "미니디스크", "category": "사물/도구" },
  { "emoji": "💾", "name": "플로피디스크", "category": "사물/도구" },
  { "emoji": "💿", "name": "CD", "category": "사물/도구" },
  { "emoji": "📀", "name": "DVD", "category": "사물/도구" },
  { "emoji": "🧮", "name": "주판", "category": "사물/도구" },
  { "emoji": "🎥", "name": "영화 카메라", "category": "사물/도구" },
  { "emoji": "🎞️", "name": "필름", "category": "사물/도구" },
  { "emoji": "📽️", "name": "프로젝터", "category": "사물/도구" },
  { "emoji": "📺", "name": "텔레비전", "category": "사물/도구" },
  { "emoji": "📸", "name": "플래시 카메라", "category": "사물/도구" },
  { "emoji": "📹", "name": "비디오 카메라", "category": "사물/도구" },
  { "emoji": "📼", "name": "비디오테이프", "category": "사물/도구" },
  { "emoji": "🔍", "name": "돋보기(왼쪽)", "category": "사물/도구" },
  { "emoji": "🔎", "name": "돋보기(오른쪽)", "category": "사물/도구" },
  { "emoji": "🕯️", "name": "양초", "category": "사물/도구" },
  { "emoji": "🔦", "name": "손전등", "category": "사물/도구" },
  { "emoji": "🏮", "name": "홍등", "category": "사물/도구" },
  { "emoji": "📔", "name": "노트", "category": "사물/도구" },
  { "emoji": "📕", "name": "빨간 책", "category": "사물/도구" },
  { "emoji": "📖", "name": "펼친 책", "category": "사물/도구" },
  { "emoji": "📗", "name": "초록 책", "category": "사물/도구" },
  { "emoji": "📘", "name": "파란 책", "category": "사물/도구" },
  { "emoji": "📙", "name": "주황 책", "category": "사물/도구" },
  { "emoji": "📚", "name": "책 더미", "category": "사물/도구" },
  { "emoji": "🔖", "name": "책갈피", "category": "사물/도구" },
  { "emoji": "🏷️", "name": "라벨", "category": "사물/도구" },
  { "emoji": "💰", "name": "돈가방", "category": "사물/도구" },
  { "emoji": "💴", "name": "엔화", "category": "사물/도구" },
  { "emoji": "💵", "name": "달러", "category": "사물/도구" },
  { "emoji": "💶", "name": "유로", "category": "사물/도구" },
  { "emoji": "💷", "name": "파운드", "category": "사물/도구" },
  { "emoji": "🪙", "name": "동전", "category": "사물/도구" },
  { "emoji": "✉️", "name": "편지", "category": "사물/도구" },
  { "emoji": "📧", "name": "이메일", "category": "사물/도구" },
  { "emoji": "📮", "name": "우체통", "category": "사물/도구" },
  { "emoji": "🗳️", "name": "투표함", "category": "사물/도구" },
  { "emoji": "✏️", "name": "연필", "category": "사물/도구" },
  { "emoji": "✒️", "name": "만년필", "category": "사물/도구" },
  { "emoji": "🖋️", "name": "펜", "category": "사물/도구" },
  { "emoji": "🖌️", "name": "붓", "category": "사물/도구" },
  { "emoji": "🖍️", "name": "크레용", "category": "사물/도구" },
  { "emoji": "📝", "name": "메모", "category": "사물/도구" },
  { "emoji": "📁", "name": "파일폴더", "category": "사물/도구" },
  { "emoji": "📂", "name": "열린 파일폴더", "category": "사물/도구" },
  { "emoji": "🗒️", "name": "메모장", "category": "사물/도구" },
  { "emoji": "📌", "name": "압정", "category": "사물/도구" },
  { "emoji": "📍", "name": "둥근 압정", "category": "사물/도구" },
  { "emoji": "📎", "name": "클립", "category": "사물/도구" },
  { "emoji": "📏", "name": "자", "category": "사물/도구" },
  { "emoji": "📐", "name": "삼각자", "category": "사물/도구" },
  { "emoji": "✂️", "name": "가위", "category": "사물/도구" },
  { "emoji": "🗃️", "name": "파일 캐비닛", "category": "사물/도구" },
  { "emoji": "🗑️", "name": "휴지통", "category": "사물/도구" },
  { "emoji": "🔐", "name": "잠긴 열쇠", "category": "사물/도구" },
  { "emoji": "🔓", "name": "열린 자물쇠", "category": "사물/도구" },
  { "emoji": "🔏", "name": "잠긴 펜", "category": "사물/도구" },
  { "emoji": "🔨", "name": "망치", "category": "사물/도구" },
  { "emoji": "🪓", "name": "도끼", "category": "사물/도구" },
  { "emoji": "⛏️", "name": "곡괭이", "category": "사물/도구" },
  { "emoji": "🔩", "name": "나사", "category": "사물/도구" },
  { "emoji": "⚙️", "name": "기어", "category": "사물/도구" },
  { "emoji": "🧱", "name": "벽돌", "category": "사물/도구" },
  { "emoji": "⛓️", "name": "사슬", "category": "사물/도구" },
  { "emoji": "🧲", "name": "자석", "category": "사물/도구" },
  { "emoji": "🔫", "name": "권총", "category": "사물/도구" },
  { "emoji": "💣", "name": "폭탄", "category": "사물/도구" },
  { "emoji": "🔪", "name": "식칼", "category": "사물/도구" },
  { "emoji": "🗡️", "name": "단검", "category": "사물/도구" },
  { "emoji": "🛡️", "name": "방패", "category": "사물/도구" },
  { "emoji": "🚬", "name": "담배", "category": "사물/도구" },
  { "emoji": "⚰️", "name": "관", "category": "사물/도구" },
  { "emoji": "⚱️", "name": "유골함", "category": "사물/도구" },
  { "emoji": "🏺", "name": "암포라", "category": "사물/도구" },
  { "emoji": "🔮", "name": "수정 구슬", "category": "사물/도구" },
  { "emoji": "📿", "name": "염주", "category": "사물/도구" },
  { "emoji": "💈", "name": "이발소", "category": "사물/도구" },
  { "emoji": "⚗️", "name": "증류기", "category": "사물/도구" },
  { "emoji": "🔭", "name": "망원경", "category": "사물/도구" },
  { "emoji": "🔬", "name": "현미경", "category": "사물/도구" },
  { "emoji": "🕳️", "name": "구멍", "category": "사물/도구" },
  { "emoji": "💊", "name": "알약", "category": "사물/도구" },
  { "emoji": "💉", "name": "주사기", "category": "사물/도구" },
  { "emoji": "🩸", "name": "혈액", "category": "사물/도구" },
  { "emoji": "🧬", "name": "DNA", "category": "사물/도구" },
  { "emoji": "🦠", "name": "미생물", "category": "사물/도구" },
  { "emoji": "🧫", "name": "페트리 접시", "category": "사물/도구" },
  { "emoji": "🧪", "name": "시험관", "category": "사물/도구" },
  { "emoji": "🌡️", "name": "체온계", "category": "사물/도구" },
  { "emoji": "🧹", "name": "빗자루", "category": "사물/도구" },
  { "emoji": "🧺", "name": "바구니", "category": "사물/도구" },
  { "emoji": "🚽", "name": "변기", "category": "사물/도구" },
  { "emoji": "🚿", "name": "샤워기", "category": "사물/도구" },
  { "emoji": "🛁", "name": "욕조", "category": "사물/도구" },
  { "emoji": "🧼", "name": "비누", "category": "사물/도구" },
  { "emoji": "🪒", "name": "면도기", "category": "사물/도구" },
  { "emoji": "🧽", "name": "스펀지", "category": "사물/도구" },
  { "emoji": "🪣", "name": "양동이", "category": "사물/도구" },
  { "emoji": "🎈", "name": "풍선", "category": "사물/도구" },
  { "emoji": "🎉", "name": "축하", "category": "사물/도구" },
  { "emoji": "🎊", "name": "오색 테이프", "category": "사물/도구" },
  { "emoji": "🎁", "name": "선물", "category": "사물/도구" },
  { "emoji": "🎀", "name": "리본", "category": "사물/도구" },
  { "emoji": "🧸", "name": "곰인형", "category": "사물/도구" },
  { "emoji": "🪆", "name": "마트료시카", "category": "사물/도구" },

  
  { "emoji": "❤️", "name": "빨간 하트", "category": "상징/기호" },
  { "emoji": "🧡", "name": "주황 하트", "category": "상징/기호" },
  { "emoji": "💛", "name": "노란 하트", "category": "상징/기호" },
  { "emoji": "💚", "name": "초록 하트", "category": "상징/기호" },
  { "emoji": "💙", "name": "파랑 하트", "category": "상징/기호" },
  { "emoji": "💜", "name": "보라 하트", "category": "상징/기호" },
  { "emoji": "🖤", "name": "검정 하트", "category": "상징/기호" },
  { "emoji": "🤍", "name": "하얀 하트", "category": "상징/기호" },
  { "emoji": "💔", "name": "부서진 하트", "category": "상징/기호" },
  { "emoji": "❣️", "name": "느낌표 하트", "category": "상징/기호" },
  { "emoji": "✔️", "name": "체크", "category": "상징/기호" },
  { "emoji": "❌", "name": "엑스", "category": "상징/기호" },
  { "emoji": "⭐", "name": "별", "category": "상징/기호" },
  { "emoji": "🌟", "name": "반짝별", "category": "상징/기호" },
  { "emoji": "🔔", "name": "종", "category": "상징/기호" },
  { "emoji": "⚠️", "name": "경고", "category": "상징/기호" },
  { "emoji": "➡️", "name": "오른쪽 화살표", "category": "기호/화살표" },
  { "emoji": "⬅️", "name": "왼쪽 화살표", "category": "기호/화살표" },
  { "emoji": "⬆️", "name": "위쪽 화살표", "category": "기호/화살표" },
  { "emoji": "⬇️", "name": "아래쪽 화살표", "category": "기호/화살표" },
  { "emoji": "↗️", "name": "오른쪽 위 화살표", "category": "기호/화살표" },
  { "emoji": "↘️", "name": "오른쪽 아래 화살표", "category": "기호/화살표" },
  { "emoji": "↙️", "name": "왼쪽 아래 화살표", "category": "기호/화살표" },
  { "emoji": "↖️", "name": "왼쪽 위 화살표", "category": "기호/화살표" },
  { "emoji": "🔃", "name": "회전", "category": "기호/화살표" },
  { "emoji": "🔄", "name": "반복", "category": "기호/화살표" },

  
  { "emoji": "💕", "name": "두개의 하트", "category": "상징/기호" },
  { "emoji": "💞", "name": "회전하는 하트", "category": "상징/기호" },
  { "emoji": "💓", "name": "두근거리는 하트", "category": "상징/기호" },
  { "emoji": "💗", "name": "커지는 하트", "category": "상징/기호" },
  { "emoji": "💖", "name": "반짝이는 하트", "category": "상징/기호" },
  { "emoji": "💘", "name": "화살 맞은 하트", "category": "상징/기호" },
  { "emoji": "💝", "name": "리본 달린 하트", "category": "상징/기호" },
  { "emoji": "💟", "name": "하트 장식", "category": "상징/기호" },
  { "emoji": "☮️", "name": "평화", "category": "상징/기호" },
  { "emoji": "✝️", "name": "십자가", "category": "상징/기호" },
  { "emoji": "☪️", "name": "초승달과 별", "category": "상징/기호" },
  { "emoji": "🕉️", "name": "옴", "category": "상징/기호" },
  { "emoji": "☸️", "name": "법륜", "category": "상징/기호" },
  { "emoji": "✡️", "name": "다윗의 별", "category": "상징/기호" },
  { "emoji": "🔯", "name": "육각별", "category": "상징/기호" },
  { "emoji": "🕎", "name": "메노라", "category": "상징/기호" },
  { "emoji": "☯️", "name": "음양", "category": "상징/기호" },
  { "emoji": "☦️", "name": "동방 정교회 십자가", "category": "상징/기호" },
  { "emoji": "🛐", "name": "예배", "category": "상징/기호" },
  { "emoji": "⛎", "name": "뱀주인자리", "category": "상징/기호" },
  { "emoji": "♈", "name": "양자리", "category": "상징/기호" },
  { "emoji": "♉", "name": "황소자리", "category": "상징/기호" },
  { "emoji": "♊", "name": "쌍둥이자리", "category": "상징/기호" },
  { "emoji": "♋", "name": "게자리", "category": "상징/기호" },
  { "emoji": "♌", "name": "사자자리", "category": "상징/기호" },
  { "emoji": "♍", "name": "처녀자리", "category": "상징/기호" },
  { "emoji": "♎", "name": "천칭자리", "category": "상징/기호" },
  { "emoji": "♏", "name": "전갈자리", "category": "상징/기호" },
  { "emoji": "♐", "name": "궁수자리", "category": "상징/기호" },
  { "emoji": "♑", "name": "염소자리", "category": "상징/기호" },
  { "emoji": "♒", "name": "물병자리", "category": "상징/기호" },
  { "emoji": "♓", "name": "물고기자리", "category": "상징/기호" },
  { "emoji": "🆔", "name": "ID", "category": "상징/기호" },
  { "emoji": "⚛️", "name": "원자", "category": "상징/기호" },
  { "emoji": "🈳", "name": "공실", "category": "상징/기호" },
  { "emoji": "🈹", "name": "할인", "category": "상징/기호" },
  { "emoji": "☢️", "name": "방사능", "category": "상징/기호" },
  { "emoji": "☣️", "name": "생물학적 위험", "category": "상징/기호" },
  { "emoji": "📴", "name": "휴대폰 꺼짐", "category": "상징/기호" },
  { "emoji": "📳", "name": "진동 모드", "category": "상징/기호" },
  { "emoji": "🈶", "name": "유료", "category": "상징/기호" },
  { "emoji": "🈚", "name": "무료", "category": "상징/기호" },
  { "emoji": "🈺", "name": "영업중", "category": "상징/기호" },
  { "emoji": "🈷️", "name": "월", "category": "상징/기호" },
  { "emoji": "✴️", "name": "팔각별", "category": "상징/기호" },
  { "emoji": "🆚", "name": "VS", "category": "상징/기호" },
  { "emoji": "🉑", "name": "가능", "category": "상징/기호" },
  { "emoji": "💮", "name": "참 잘했어요", "category": "상징/기호" },
  { "emoji": "🉐", "name": "득템", "category": "상징/기호" },
  { "emoji": "㊙️", "name": "비밀", "category": "상징/기호" },
  { "emoji": "㊗️", "name": "축하", "category": "상징/기호" },
  { "emoji": "🈴", "name": "합격", "category": "상징/기호" },
  { "emoji": "🈵", "name": "만실", "category": "상징/기호" },
  { "emoji": "🈲", "name": "금지", "category": "상징/기호" },
  { "emoji": "🅰️", "name": "A형", "category": "상징/기호" },
  { "emoji": "🅱️", "name": "B형", "category": "상징/기호" },
  { "emoji": "🆎", "name": "AB형", "category": "상징/기호" },
  { "emoji": "🆑", "name": "취소", "category": "상징/기호" },
  { "emoji": "🅾️", "name": "O형", "category": "상징/기호" },
  { "emoji": "🆘", "name": "SOS", "category": "상징/기호" },
  { "emoji": "⛔", "name": "진입금지", "category": "상징/기호" },
  { "emoji": "📛", "name": "이름표", "category": "상징/기호" },
  { "emoji": "🚫", "name": "금지", "category": "상징/기호" },
  { "emoji": "🚭", "name": "금연", "category": "상징/기호" },
  { "emoji": "🚮", "name": "쓰레기 버리는 곳", "category": "상징/기호" },
  { "emoji": "🚱", "name": "식수 아님", "category": "상징/기호" },
  { "emoji": "🔞", "name": "18세 미만 금지", "category": "상징/기호" },
  { "emoji": "📵", "name": "휴대폰 금지", "category": "상징/기호" },
  { "emoji": "❗", "name": "느낌표", "category": "상징/기호" },
  { "emoji": "❓", "name": "물음표", "category": "상징/기호" },
  { "emoji": "❔", "name": "하얀 물음표", "category": "상징/기호" },
  { "emoji": "❕", "name": "하얀 느낌표", "category": "상징/기호" },
  { "emoji": "💯", "name": "100점", "category": "상징/기호" },
  { "emoji": "🔙", "name": "BACK 화살표", "category": "기호/화살표" },
  { "emoji": "🔚", "name": "END 화살표", "category": "기호/화살표" },
  { "emoji": "🔛", "name": "ON! 화살표", "category": "기호/화살표" },
  { "emoji": "🔜", "name": "SOON 화살표", "category": "기호/화살표" },
  { "emoji": "🔝", "name": "TOP 화살표", "category": "기호/화살표" },
  { "emoji": "🔰", "name": "초보자 마크", "category": "상징/기호" },
  { "emoji": "⚜️", "name": "백합 문장", "category": "상징/기호" },
  { "emoji": "♻️", "name": "재활용", "category": "상징/기호" },
  { "emoji": "✅", "name": "흰색 체크", "category": "상징/기호" },
  { "emoji": "🈯", "name": "지정", "category": "상징/기호" },
  { "emoji": "💹", "name": "주가 상승", "category": "상징/기호" },
  { "emoji": "❇️", "name": "반짝임", "category": "상징/기호" },
  { "emoji": "✳️", "name": "별표", "category": "상징/기호" },
  { "emoji": "❎", "name": "엑스 버튼", "category": "상징/기호" },
  { "emoji": "➿", "name": "이중 곱슬 루프", "category": "상징/기호" },
  { "emoji": "TM", "name": "상표", "category": "상징/기호" },
  { "emoji": "#️⃣", "name": "해시태그", "category": "상징/기호" },
  { "emoji": "*️⃣", "name": "별표 키", "category": "상징/기호" },
  { "emoji": "0️⃣", "name": "숫자 0", "category": "상징/기호" },
  { "emoji": "1️⃣", "name": "숫자 1", "category": "상징/기호" },
  { "emoji": "2️⃣", "name": "숫자 2", "category": "상징/기호" },
  { "emoji": "3️⃣", "name": "숫자 3", "category": "상징/기호" },
  { "emoji": "4️⃣", "name": "숫자 4", "category": "상징/기호" },
  { "emoji": "5️⃣", "name": "숫자 5", "category": "상징/기호" },
  { "emoji": "6️⃣", "name": "숫자 6", "category": "상징/기호" },
  { "emoji": "7️⃣", "name": "숫자 7", "category": "상징/기호" },
  { "emoji": "8️⃣", "name": "숫자 8", "category": "상징/기호" },
  { "emoji": "9️⃣", "name": "숫자 9", "category": "상징/기호" },
  { "emoji": "🔟", "name": "숫자 10", "category": "상징/기호" },
  { "emoji": "🔠", "name": "알파벳 대문자", "category": "상징/기호" },
  { "emoji": "🔡", "name": "알파벳 소문자", "category": "상징/기호" },
  { "emoji": "🔢", "name": "숫자 입력", "category": "상징/기호" },
  { "emoji": "🔣", "name": "기호 입력", "category": "상징/기호" },
  { "emoji": "🏳️", "name": "흰 깃발", "category": "상징/기호" },
  { "emoji": "🏴", "name": "검은 깃발", "category": "상징/기호" },
  { "emoji": "🏁", "name": "체커기", "category": "상징/기호" },
  { "emoji": "🚩", "name": "삼각 깃발", "category": "상징/기호" },
  { "emoji": "🎌", "name": "교차 깃발", "category": "상징/기호" },
  { "emoji": "🏳️‍🌈", "name": "무지개 깃발", "category": "상징/기호" },
  { "emoji": "🏳️‍⚧️", "name": "트랜스젠더 깃발", "category": "상징/기호" }
]